__init__.py
pyphrase/__init__.py
pyphrase/asynchron/__init__.py
pyphrase/asynchron/client.py
pyphrase/asynchron/tags/__init__.py
pyphrase/asynchron/tags/additional_workflow_step.py
pyphrase/asynchron/tags/analysis.py
pyphrase/asynchron/tags/async_request.py
pyphrase/asynchron/tags/authentication.py
pyphrase/asynchron/tags/automations.py
pyphrase/asynchron/tags/bilingual_file.py
pyphrase/asynchron/tags/business_unit.py
pyphrase/asynchron/tags/client.py
pyphrase/asynchron/tags/connector.py
pyphrase/asynchron/tags/conversations.py
pyphrase/asynchron/tags/cost_center.py
pyphrase/asynchron/tags/custom_fields.py
pyphrase/asynchron/tags/custom_file_type.py
pyphrase/asynchron/tags/domain.py
pyphrase/asynchron/tags/email_template.py
pyphrase/asynchron/tags/file.py
pyphrase/asynchron/tags/glossary.py
pyphrase/asynchron/tags/import_settings.py
pyphrase/asynchron/tags/job.py
pyphrase/asynchron/tags/language_ai.py
pyphrase/asynchron/tags/language_quality_assessment.py
pyphrase/asynchron/tags/machine_translation.py
pyphrase/asynchron/tags/machine_translation_settings.py
pyphrase/asynchron/tags/mapping.py
pyphrase/asynchron/tags/net_rate_scheme.py
pyphrase/asynchron/tags/price_list.py
pyphrase/asynchron/tags/project.py
pyphrase/asynchron/tags/project_reference_file.py
pyphrase/asynchron/tags/project_template.py
pyphrase/asynchron/tags/provider.py
pyphrase/asynchron/tags/quality_assurance.py
pyphrase/asynchron/tags/quote.py
pyphrase/asynchron/tags/scim.py
pyphrase/asynchron/tags/segmentation_rules.py
pyphrase/asynchron/tags/spell_check.py
pyphrase/asynchron/tags/subdomain.py
pyphrase/asynchron/tags/supported_languages.py
pyphrase/asynchron/tags/term_base.py
pyphrase/asynchron/tags/translation.py
pyphrase/asynchron/tags/translation_memory.py
pyphrase/asynchron/tags/user.py
pyphrase/asynchron/tags/vendor.py
pyphrase/asynchron/tags/webhook.py
pyphrase/asynchron/tags/workflow_changes.py
pyphrase/asynchron/tags/workflow_step.py
pyphrase/asynchron/tags/xml_assistant.py
pyphrase-0.3.0.dist-info/LICENCE
pyphrase-0.3.0.dist-info/METADATA
pyphrase-0.3.0.dist-info/WHEEL
pyphrase-0.3.0.dist-info/top_level.txt
pyphrase-0.3.0.dist-info/RECORD
