Metadata-Version: 2.1
Name: pyphrase
Version: 0.3.0
Summary: Client for the Phrase TMS API.
Author-email: Henrik Kühnemann <hello@yellownape.se>
Project-URL: Homepage, https://github.com/kuhnemann/pyphrase
Keywords: phrase tms,memsource,api,translation,localization,tms
Classifier: License :: OSI Approved :: MIT License
Classifier: Programming Language :: Python
Classifier: Programming Language :: Python :: 3
Requires-Python: >=3.9
License-File: LICENCE
Requires-Dist: pydantic >=1.10
Requires-Dist: httpx >=0.23
Provides-Extra: dev
Requires-Dist: black ; extra == 'dev'
Requires-Dist: bumpver ; extra == 'dev'
Requires-Dist: isort ; extra == 'dev'
Requires-Dist: pip-tools ; extra == 'dev'
Requires-Dist: pytest ; extra == 'dev'
